keelet_cli/__about__.py
keelet_cli/__init__.py
keelet_cli-0.0.1.dist-info/METADATA
keelet_cli-0.0.1.dist-info/WHEEL
keelet_cli-0.0.1.dist-info/entry_points.txt
keelet_cli-0.0.1.dist-info/licenses/LICENSE.txt
keelet_cli-0.0.1.dist-info/RECORD
